incipio/__init__.py
incipio/package.py
incipio-0.1.0.dist-info/DESCRIPTION.rst
incipio-0.1.0.dist-info/METADATA
incipio-0.1.0.dist-info/RECORD
incipio-0.1.0.dist-info/WHEEL
incipio-0.1.0.dist-info/metadata.json
incipio-0.1.0.dist-info/top_level.txt
